esa_2scm/LICENSE
esa_2scm/__init__.py
esa_2scm/models.py
esa_2scm/syniv/__init__.py
esa_2scm/syniv/esa.py
esa_2scm-1.0.0.dist-info/LICENSE
esa_2scm-1.0.0.dist-info/METADATA
esa_2scm-1.0.0.dist-info/WHEEL
esa_2scm-1.0.0.dist-info/top_level.txt
esa_2scm-1.0.0.dist-info/RECORD
