Metadata-Version: 2.1
Name: esa-2scm
Version: 1.0.0
Summary: ESA-2SCM Python Package for Causal Discovery
Home-page: https://github.com/DSsoli/esa-2scm.git
Author: Sanghoon Lee (DSsoli)
Author-email: solisoli3197@gmail.com
License-File: LICENSE
Requires-Dist: numpy
Requires-Dist: pandas
Requires-Dist: scipy
Requires-Dist: scikit-learn
